{"textures":{"8":"walmart:entity/battle_bot/texture"},"elements":[{"faces":{"north":{"uv":[3.996,7.246,3.504,7.129],"texture":"#8","tintindex":0},"east":{"uv":[3.621,7.246,3.504,5.629],"rotation":90,"texture":"#8","tintindex":0},"south":{"uv":[3.996,5.746,3.504,5.629],"texture":"#8","tintindex":0},"west":{"uv":[3.621,5.629,3.504,7.246],"rotation":90,"texture":"#8","tintindex":0},"up":{"uv":[3.996,7.246,3.504,5.629],"texture":"#8","tintindex":0},"down":{"uv":[3.996,5.629,3.504,7.246],"texture":"#8","tintindex":0}},"to":[11.2,5.8,9.6],"from":[4.8,4.2,-11.2],"rotation":{"angle":0,"axis":"y","origin":[-11.2,-39,-6.4]}}],"display":{"head":{"translation":[0,-3.2,0],"scale":[1,1,1],"rotation":[0,0,0]}}}