{
	"credit": "Made by Ziqqy using Blockbench",
	"parent": "walmart:display_parents/furniture",
	"texture_size": [512, 512],
	"textures": {
		"1": "walmart:furniture/futuristic_truck",
		"particle": "walmart:furniture/futuristic_truck"
	},
	"elements": [
		{
			"from": [0.75, 3.75, 0.5],
			"to": [15.25, 17.25, 19.5],
			"rotation": {"angle": 0, "axis": "y", "origin": [7.75, 2.5, 9.75]},
			"faces": {
				"north": {"uv": [0.001, 4.8135, 1.8115, 6.499], "texture": "#1", "tintindex": 0},
				"east": {"uv": [6.124, 0.001, 3.751, 1.6865], "texture": "#1", "tintindex": 0},
				"south": {"uv": [1.8135, 4.8135, 3.624, 6.499], "texture": "#1", "tintindex": 0},
				"west": {"uv": [3.751, 0.001, 6.124, 1.6865], "texture": "#1", "tintindex": 0},
				"up": {"uv": [1.8115, 4.8115, 0.001, 2.4385], "texture": "#1", "tintindex": 0},
				"down": {"uv": [3.624, 2.4385, 1.8135, 4.8115], "texture": "#1", "tintindex": 0}
			}
		},
		{
			"from": [2.625, 11.75, -5.5],
			"to": [13.375, 12.5, 0.5],
			"rotation": {"angle": 0, "axis": "y", "origin": [7.75, 2.5, -9]},
			"faces": {
				"north": {"uv": [6.5635, 4.28225, 7.90525, 4.374], "texture": "#1"},
				"east": {"uv": [7.4365, 0.001, 6.6885, 0.09275], "texture": "#1"},
				"west": {"uv": [6.6885, 0.001, 7.4365, 0.09275], "texture": "#1"},
				"up": {"uv": [5.09275, 2.4365, 3.751, 1.6885], "texture": "#1"},
				"down": {"uv": [6.4365, 1.6885, 5.09475, 2.4365], "texture": "#1"}
			}
		},
		{
			"from": [-1.5, 2.75, 13.25],
			"to": [3, 4.75, 17.75],
			"rotation": {"angle": -22.5, "axis": "z", "origin": [0.75, 3.75, 15.5]},
			"faces": {
				"north": {"uv": [4.71975, 6.53225, 5.28025, 6.78025], "texture": "#1"},
				"east": {"uv": [4.71975, 6.53225, 5.28025, 6.78025], "texture": "#1"},
				"south": {"uv": [4.71975, 6.53225, 5.28025, 6.78025], "texture": "#1"},
				"west": {"uv": [4.71975, 6.53225, 5.28025, 6.78025], "texture": "#1"},
				"up": {"uv": [6.6865, 0.5615, 6.126, 0.001], "texture": "#1"},
				"down": {"uv": [6.6865, 0.5635, 6.126, 1.124], "texture": "#1"}
			}
		},
		{
			"from": [1.09567, 1.98097, -3.5],
			"to": [4.59567, 3.98097, 0],
			"rotation": {"angle": -22.5, "axis": "z", "origin": [2.84567, 2.98097, -1.75]},
			"faces": {
				"north": {"uv": [6.5635, 4.376, 6.999, 4.624], "texture": "#1"},
				"east": {"uv": [6.5635, 4.376, 6.999, 4.624], "texture": "#1"},
				"south": {"uv": [6.5635, 4.376, 6.999, 4.624], "texture": "#1"},
				"west": {"uv": [6.5635, 4.376, 6.999, 4.624], "texture": "#1"},
				"up": {"uv": [6.874, 2.0615, 6.4385, 1.626], "texture": "#1"},
				"down": {"uv": [0.4365, 6.501, 0.001, 6.9365], "texture": "#1"}
			}
		},
		{
			"from": [-0.92336, 2.6353, 8.75],
			"to": [2.57664, 4.6353, 12.25],
			"rotation": {"angle": -22.5, "axis": "z", "origin": [1.07664, 3.6353, 10.75]},
			"faces": {
				"north": {"uv": [6.5635, 4.626, 6.999, 4.874], "texture": "#1"},
				"east": {"uv": [6.5635, 4.626, 6.999, 4.874], "texture": "#1"},
				"south": {"uv": [6.5635, 4.626, 6.999, 4.874], "texture": "#1"},
				"west": {"uv": [6.5635, 4.626, 6.999, 4.874], "texture": "#1"},
				"up": {"uv": [0.874, 6.9365, 0.4385, 6.501], "texture": "#1"},
				"down": {"uv": [1.3115, 6.501, 0.876, 6.9365], "texture": "#1"}
			}
		},
		{
			"from": [1.5, 1.5, 2.25],
			"to": [3.5, 3.5, 7.75],
			"rotation": {"angle": 0, "axis": "y", "origin": [8.5, 0.25, 4.75]},
			"faces": {
				"north": {"uv": [6.09475, 6.71975, 6.34275, 6.96775], "texture": "#1"},
				"east": {"uv": [1.9385, 6.501, 2.624, 6.749], "texture": "#1"},
				"south": {"uv": [6.34475, 6.71975, 6.59275, 6.96775], "texture": "#1"},
				"west": {"uv": [2.626, 6.501, 3.3115, 6.749], "texture": "#1"},
				"up": {"uv": [3.5615, 7.1865, 3.3135, 6.501], "texture": "#1"},
				"down": {"uv": [5.71775, 6.501, 5.46975, 7.1865], "texture": "#1"}
			}
		},
		{
			"from": [1.375, 1.375, 3],
			"to": [3.625, 4.125, 3.75],
			"rotation": {"angle": 0, "axis": "y", "origin": [8.5, 0.25, 3.5]},
			"faces": {
				"east": {"uv": [3.8135, 6.8135, 3.90525, 7.15525], "texture": "#1"},
				"west": {"uv": [3.90725, 6.8135, 3.999, 7.15525], "texture": "#1"},
				"down": {"uv": [7.09275, 0.501, 6.8135, 0.59275], "texture": "#1"}
			}
		},
		{
			"from": [1.375, 1.375, 6.25],
			"to": [3.625, 4.125, 7],
			"rotation": {"angle": 0, "axis": "y", "origin": [8.5, 0.25, 6.5]},
			"faces": {
				"east": {"uv": [4.001, 6.8135, 4.09275, 7.15525], "texture": "#1"},
				"west": {"uv": [4.09475, 6.8135, 4.1865, 7.15525], "texture": "#1"},
				"down": {"uv": [7.09275, 5.001, 6.8135, 5.09275], "texture": "#1"}
			}
		},
		{
			"from": [12.375, 1.375, 3],
			"to": [14.625, 4.125, 3.75],
			"rotation": {"angle": 0, "axis": "y", "origin": [7.5, 0.25, 3.5]},
			"faces": {
				"east": {"uv": [3.999, 6.8135, 3.90725, 7.15525], "texture": "#1"},
				"west": {"uv": [3.90525, 6.8135, 3.8135, 7.15525], "texture": "#1"},
				"down": {"uv": [6.8135, 0.501, 7.09275, 0.59275], "texture": "#1"}
			}
		},
		{
			"from": [12.5, 1.5, 2.25],
			"to": [14.5, 3.5, 7.75],
			"rotation": {"angle": 0, "axis": "y", "origin": [7.5, 0.25, 4.75]},
			"faces": {
				"north": {"uv": [6.34275, 6.71975, 6.09475, 6.96775], "texture": "#1"},
				"east": {"uv": [3.3115, 6.501, 2.626, 6.749], "texture": "#1"},
				"south": {"uv": [6.59275, 6.71975, 6.34475, 6.96775], "texture": "#1"},
				"west": {"uv": [2.624, 6.501, 1.9385, 6.749], "texture": "#1"},
				"up": {"uv": [3.3135, 7.1865, 3.5615, 6.501], "texture": "#1"},
				"down": {"uv": [5.46975, 6.501, 5.71775, 7.1865], "texture": "#1"}
			}
		},
		{
			"from": [12.375, 1.375, 6.25],
			"to": [14.625, 4.125, 7],
			"rotation": {"angle": 0, "axis": "y", "origin": [7.5, 0.25, 6.5]},
			"faces": {
				"east": {"uv": [4.1865, 6.8135, 4.09475, 7.15525], "texture": "#1"},
				"west": {"uv": [4.09275, 6.8135, 4.001, 7.15525], "texture": "#1"},
				"down": {"uv": [6.8135, 5.001, 7.09275, 5.09275], "texture": "#1"}
			}
		},
		{
			"from": [0.5, 3.5, 0.25],
			"to": [15.5, 17.5, 19.75],
			"rotation": {"angle": 0, "axis": "y", "origin": [7.75, 2.5, 9.75]},
			"faces": {
				"north": {"uv": [3.626, 4.1885, 5.499, 5.9365], "texture": "#1", "tintindex": 0},
				"east": {"uv": [6.0615, 2.4385, 3.626, 4.1865], "texture": "#1", "tintindex": 0},
				"south": {"uv": [5.499, 4.1885, 3.626, 5.9365], "texture": "#1", "tintindex": 0},
				"west": {"uv": [3.626, 2.4385, 6.0615, 4.1865], "texture": "#1", "tintindex": 0},
				"up": {"uv": [1.874, 2.4365, 0.001, 0.001], "texture": "#1", "tintindex": 0},
				"down": {"uv": [3.749, 0.001, 1.876, 2.4365], "texture": "#1", "tintindex": 0}
			}
		},
		{
			"from": [2, 2, -7.75],
			"to": [14, 3.75, -7.25],
			"rotation": {"angle": -22.5, "axis": "x", "origin": [8, 2.875, -7.5]},
			"faces": {
				"north": {"uv": [6.0635, 3.59475, 7.5615, 3.8115], "texture": "#1"},
				"east": {"uv": [6.876, 3.376, 6.9365, 3.59275], "texture": "#1"},
				"south": {"uv": [6.0635, 3.8135, 7.5615, 4.03025], "texture": "#1"},
				"west": {"uv": [4.6885, 6.90725, 4.749, 7.124], "texture": "#1"},
				"up": {"uv": [8.0615, 4.9365, 6.5635, 4.876], "texture": "#1"},
				"down": {"uv": [8.0615, 4.9385, 6.5635, 4.999], "texture": "#1"}
			}
		},
		{
			"from": [2, 2, -7.25],
			"to": [2.5, 3.75, -5.75],
			"rotation": {"angle": -22.5, "axis": "x", "origin": [8, 2.875, -7.5]},
			"faces": {
				"north": {"uv": [4.751, 6.90725, 4.8115, 7.124], "texture": "#1"},
				"east": {"uv": [5.0635, 6.78225, 5.249, 6.999], "texture": "#1"},
				"south": {"uv": [4.8135, 6.90725, 4.874, 7.124], "texture": "#1"},
				"west": {"uv": [6.8135, 0.21975, 6.999, 0.4365], "texture": "#1"},
				"up": {"uv": [6.96775, 6.53025, 6.90725, 6.34475], "texture": "#1"},
				"down": {"uv": [6.96775, 6.84475, 6.90725, 7.03025], "texture": "#1"}
			}
		},
		{
			"from": [13.5, 2, -7.25],
			"to": [14, 3.75, -5.75],
			"rotation": {"angle": -22.5, "axis": "x", "origin": [8, 2.875, -7.5]},
			"faces": {
				"north": {"uv": [4.8115, 6.90725, 4.751, 7.124], "texture": "#1"},
				"east": {"uv": [6.999, 0.21975, 6.8135, 0.4365], "texture": "#1"},
				"south": {"uv": [4.874, 6.90725, 4.8135, 7.124], "texture": "#1"},
				"west": {"uv": [5.249, 6.78225, 5.0635, 6.999], "texture": "#1"},
				"up": {"uv": [6.90725, 6.53025, 6.96775, 6.34475], "texture": "#1"},
				"down": {"uv": [6.90725, 6.84475, 6.96775, 7.03025], "texture": "#1"}
			}
		},
		{
			"from": [6, 2.58772, -8.31582],
			"to": [10, 4.08772, -8.06582],
			"rotation": {"angle": 0, "axis": "y", "origin": [8, 4.46272, -8.31582]},
			"faces": {
				"north": {"uv": [3.8135, 6.626, 4.3115, 6.8115], "texture": "#1"},
				"south": {"uv": [4.3115, 6.626, 3.8135, 6.8115], "texture": "#1"}
			}
		},
		{
			"from": [5.5, 4.25, -7.5],
			"to": [10.5, 6.5, -7],
			"rotation": {"angle": 0, "axis": "y", "origin": [7.75, 2.5, -9]},
			"faces": {
				"north": {"uv": [1.3135, 6.501, 1.9365, 6.78025], "texture": "#1"},
				"east": {"uv": [1.874, 7.15725, 1.8135, 7.4365], "texture": "#1"},
				"west": {"uv": [1.8135, 7.15725, 1.874, 7.4365], "texture": "#1"},
				"up": {"uv": [1.1885, 7.15725, 1.8115, 7.21775], "texture": "#1"},
				"down": {"uv": [1.1885, 7.376, 1.8115, 7.4365], "texture": "#1"}
			}
		},
		{
			"from": [3.25, 4, -7.25],
			"to": [5, 6.25, -7],
			"rotation": {"angle": 0, "axis": "y", "origin": [7.75, 2.5, -9]},
			"faces": {
				"north": {"uv": [1.9385, 6.751, 2.15525, 7.03025], "texture": "#1"},
				"east": {"uv": [1.9385, 6.751, 1.96775, 7.03025], "texture": "#1"},
				"west": {"uv": [1.9385, 6.751, 1.96775, 7.03025], "texture": "#1"},
				"up": {"uv": [1.9385, 6.751, 2.15525, 6.78025], "texture": "#1"},
				"down": {"uv": [1.9385, 7.001, 2.15525, 7.03025], "texture": "#1"}
			}
		},
		{
			"from": [2.875, 8.66239, -10.10057],
			"to": [3.625, 14.16239, -9.35057],
			"rotation": {"angle": 22.5, "axis": "x", "origin": [7.75, 0.16239, -12.10057]},
			"faces": {
				"north": {"uv": [5.71975, 6.71975, 5.8115, 7.40525], "texture": "#1"},
				"east": {"uv": [5.8135, 6.71975, 5.90525, 7.40525], "texture": "#1"},
				"south": {"uv": [5.90725, 6.71975, 5.999, 7.40525], "texture": "#1"},
				"west": {"uv": [6.001, 6.71975, 6.09275, 7.40525], "texture": "#1"}
			}
		},
		{
			"from": [3, 7.25, -7],
			"to": [3, 12, -1],
			"rotation": {"angle": 0, "axis": "y", "origin": [7.75, 2.5, -9]},
			"faces": {
				"west": {"uv": [4.71975, 5.9385, 5.46775, 6.53025], "texture": "#1"}
			}
		},
		{
			"from": [1.125, 7.5, -6.375],
			"to": [2.875, 9.25, -6.375],
			"rotation": {"angle": 22.5, "axis": "y", "origin": [2.875, 7.75, -6.375]},
			"faces": {
				"north": {"uv": [1.6885, 6.78225, 1.90525, 6.999], "texture": "#1"},
				"south": {"uv": [1.90525, 6.78225, 1.6885, 6.999], "texture": "#1"}
			}
		},
		{
			"from": [0.625, 8.25, -6.3125],
			"to": [2.125, 10.5, -5.8125],
			"rotation": {"angle": 22.5, "axis": "y", "origin": [2.875, 7.75, -6.375]},
			"faces": {
				"north": {"uv": [1.3135, 6.78225, 1.499, 7.0615], "texture": "#1"},
				"east": {"uv": [4.1885, 6.8135, 4.249, 7.09275], "texture": "#1"},
				"south": {"uv": [1.501, 6.78225, 1.6865, 7.0615], "texture": "#1"},
				"west": {"uv": [4.251, 6.8135, 4.3115, 7.09275], "texture": "#1"},
				"up": {"uv": [6.3115, 1.6865, 6.126, 1.626], "texture": "#1"},
				"down": {"uv": [0.1865, 6.9385, 0.001, 6.999], "texture": "#1"}
			}
		},
		{
			"from": [13.875, 8.25, -6.3125],
			"to": [15.375, 10.5, -5.8125],
			"rotation": {"angle": -22.5, "axis": "y", "origin": [13.125, 7.75, -6.375]},
			"faces": {
				"north": {"uv": [1.499, 6.78225, 1.3135, 7.0615], "texture": "#1"},
				"east": {"uv": [4.3115, 6.8135, 4.251, 7.09275], "texture": "#1"},
				"south": {"uv": [1.6865, 6.78225, 1.501, 7.0615], "texture": "#1"},
				"west": {"uv": [4.249, 6.8135, 4.1885, 7.09275], "texture": "#1"},
				"up": {"uv": [6.126, 1.6865, 6.3115, 1.626], "texture": "#1"},
				"down": {"uv": [0.001, 6.9385, 0.1865, 6.999], "texture": "#1"}
			}
		},
		{
			"from": [13.125, 7.5, -6.375],
			"to": [14.875, 9.25, -6.375],
			"rotation": {"angle": -22.5, "axis": "y", "origin": [13.125, 7.75, -6.375]},
			"faces": {
				"north": {"uv": [1.90525, 6.78225, 1.6885, 6.999], "texture": "#1"},
				"south": {"uv": [1.6885, 6.78225, 1.90525, 6.999], "texture": "#1"}
			}
		},
		{
			"from": [3.625, 8.66239, -9.85057],
			"to": [12.375, 14.16239, -9.85057],
			"rotation": {"angle": 22.5, "axis": "x", "origin": [7.75, 0.16239, -12.10057]},
			"faces": {
				"north": {"uv": [3.626, 5.9385, 4.71775, 6.624], "texture": "#1"}
			}
		},
		{
			"from": [2.75, 2.5, -7],
			"to": [13.25, 7.25, -6],
			"rotation": {"angle": 0, "axis": "y", "origin": [7.75, 2.5, -9]},
			"faces": {
				"north": {"uv": [5.501, 5.001, 6.8115, 5.59275], "texture": "#1"},
				"east": {"uv": [4.4365, 6.626, 4.3135, 7.21775], "texture": "#1"},
				"south": {"uv": [5.501, 5.59475, 6.8115, 6.1865], "texture": "#1"},
				"west": {"uv": [4.3135, 6.626, 4.4365, 7.21775], "texture": "#1"},
				"up": {"uv": [7.374, 4.15525, 6.0635, 4.03225], "texture": "#1"},
				"down": {"uv": [7.749, 2.28225, 6.4385, 2.40525], "texture": "#1"}
			}
		},
		{
			"from": [2.75, 2.5, -6],
			"to": [3.75, 7.25, 0.5],
			"rotation": {"angle": 0, "axis": "y", "origin": [7.75, 2.5, -9]},
			"faces": {
				"north": {"uv": [4.4385, 6.626, 4.5615, 7.21775], "texture": "#1"},
				"south": {"uv": [4.5635, 6.626, 4.6865, 7.21775], "texture": "#1"},
				"west": {"uv": [6.0635, 3.001, 6.874, 3.59275], "texture": "#1"},
				"up": {"uv": [3.6865, 7.4365, 3.5635, 6.626], "texture": "#1"},
				"down": {"uv": [3.8115, 6.626, 3.6885, 7.4365], "texture": "#1"}
			}
		},
		{
			"from": [3.75, 2.5, -6],
			"to": [12.25, 4, 0.5],
			"rotation": {"angle": 0, "axis": "y", "origin": [7.75, 2.5, -9]},
			"faces": {
				"east": {"uv": [5.71975, 6.53225, 6.53025, 6.71775], "texture": "#1"},
				"south": {"uv": [6.126, 1.4385, 7.1865, 1.624], "texture": "#1"},
				"west": {"uv": [6.53225, 6.53225, 7.34275, 6.71775], "texture": "#1"},
				"down": {"uv": [6.5615, 4.1885, 5.501, 4.999], "texture": "#1"}
			}
		},
		{
			"from": [3.5, 4.75, -7.375],
			"to": [4.75, 6, -7.375],
			"rotation": {"angle": 0, "axis": "y", "origin": [7.75, 2.5, -9]},
			"faces": {
				"north": {"uv": [6.8135, 5.09475, 6.96775, 5.249], "texture": "#1"}
			}
		},
		{
			"from": [3.5, 4.25, -7.375],
			"to": [4.75, 4.5, -7.375],
			"rotation": {"angle": 0, "axis": "y", "origin": [7.75, 2.5, -9]},
			"faces": {
				"north": {"uv": [6.0635, 4.15725, 6.21775, 4.1865], "texture": "#1"}
			}
		},
		{
			"from": [11.25, 4.75, -7.375],
			"to": [12.5, 6, -7.375],
			"rotation": {"angle": 0, "axis": "y", "origin": [8.25, 2.5, -9]},
			"faces": {
				"north": {"uv": [6.96775, 5.09475, 6.8135, 5.249], "texture": "#1"}
			}
		},
		{
			"from": [11, 4, -7.25],
			"to": [12.75, 6.25, -7],
			"rotation": {"angle": 0, "axis": "y", "origin": [8.25, 2.5, -9]},
			"faces": {
				"north": {"uv": [2.15525, 6.751, 1.9385, 7.03025], "texture": "#1"},
				"east": {"uv": [1.96775, 6.751, 1.9385, 7.03025], "texture": "#1"},
				"west": {"uv": [1.96775, 6.751, 1.9385, 7.03025], "texture": "#1"},
				"up": {"uv": [2.15525, 6.751, 1.9385, 6.78025], "texture": "#1"},
				"down": {"uv": [2.15525, 7.001, 1.9385, 7.03025], "texture": "#1"}
			}
		},
		{
			"from": [11.25, 4.25, -7.375],
			"to": [12.5, 4.5, -7.375],
			"rotation": {"angle": 0, "axis": "y", "origin": [8.25, 2.5, -9]},
			"faces": {
				"north": {"uv": [6.21775, 4.15725, 6.0635, 4.1865], "texture": "#1"}
			}
		},
		{
			"from": [-0.25, 2.25, 20.5],
			"to": [16.25, 4.5, 21],
			"rotation": {"angle": 0, "axis": "y", "origin": [7.75, 2.5, 9.75]},
			"faces": {
				"north": {"uv": [6.0635, 2.4385, 8.124, 2.71775], "texture": "#1"},
				"east": {"uv": [6.59475, 6.84475, 6.65525, 7.124], "texture": "#1"},
				"south": {"uv": [6.0635, 2.71975, 8.124, 2.999], "texture": "#1"},
				"west": {"uv": [6.65725, 6.84475, 6.71775, 7.124], "texture": "#1"},
				"up": {"uv": [8.624, 4.21775, 6.5635, 4.15725], "texture": "#1"},
				"down": {"uv": [8.624, 4.21975, 6.5635, 4.28025], "texture": "#1"}
			}
		},
		{
			"from": [2.75, 7.25, -1],
			"to": [3.75, 11.75, 0.5],
			"rotation": {"angle": 0, "axis": "y", "origin": [7.75, 2.5, -9]},
			"faces": {
				"north": {"uv": [6.6885, 0.09475, 6.8115, 0.65525], "texture": "#1"},
				"west": {"uv": [5.28225, 6.53225, 5.46775, 7.09275], "texture": "#1"}
			}
		},
		{
			"from": [12.25, 2.5, -6],
			"to": [13.25, 7.25, 0.5],
			"rotation": {"angle": 0, "axis": "y", "origin": [8.25, 2.5, -9]},
			"faces": {
				"north": {"uv": [4.5615, 6.626, 4.4385, 7.21775], "texture": "#1"},
				"east": {"uv": [6.874, 3.001, 6.0635, 3.59275], "texture": "#1"},
				"south": {"uv": [4.6865, 6.626, 4.5635, 7.21775], "texture": "#1"},
				"up": {"uv": [3.5635, 7.4365, 3.6865, 6.626], "texture": "#1"},
				"down": {"uv": [3.6885, 6.626, 3.8115, 7.4365], "texture": "#1"}
			}
		},
		{
			"from": [13, 7.25, -7],
			"to": [13, 12, -1],
			"rotation": {"angle": 0, "axis": "y", "origin": [8.25, 2.5, -9]},
			"faces": {
				"east": {"uv": [5.46775, 5.9385, 4.71975, 6.53025], "texture": "#1"}
			}
		},
		{
			"from": [12.25, 7.25, -1],
			"to": [13.25, 11.75, 0.5],
			"rotation": {"angle": 0, "axis": "y", "origin": [8.25, 2.5, -9]},
			"faces": {
				"north": {"uv": [6.8115, 0.09475, 6.6885, 0.65525], "texture": "#1"},
				"east": {"uv": [5.46775, 6.53225, 5.28225, 7.09275], "texture": "#1"}
			}
		},
		{
			"from": [12.375, 8.66239, -10.10057],
			"to": [13.125, 14.16239, -9.35057],
			"rotation": {"angle": 22.5, "axis": "x", "origin": [8.25, 0.16239, -12.10057]},
			"faces": {
				"north": {"uv": [5.8115, 6.71975, 5.71975, 7.40525], "texture": "#1"},
				"east": {"uv": [6.09275, 6.71975, 6.001, 7.40525], "texture": "#1"},
				"south": {"uv": [5.999, 6.71975, 5.90725, 7.40525], "texture": "#1"},
				"west": {"uv": [5.90525, 6.71975, 5.8135, 7.40525], "texture": "#1"}
			}
		},
		{
			"from": [4.625, 13.25, -2],
			"to": [11.375, 15, 0.5],
			"rotation": {"angle": 0, "axis": "y", "origin": [7.75, 2.5, -9]},
			"faces": {
				"north": {"uv": [6.4385, 2.0635, 7.28025, 2.28025], "texture": "#1"},
				"east": {"uv": [6.999, 0.84475, 6.6885, 1.0615], "texture": "#1"},
				"west": {"uv": [6.6885, 0.84475, 6.999, 1.0615], "texture": "#1"},
				"up": {"uv": [6.96775, 1.4365, 6.126, 1.126], "texture": "#1"},
				"down": {"uv": [6.3115, 6.1885, 5.46975, 6.499], "texture": "#1"}
			}
		},
		{
			"from": [5.625, 12.5, -3.5],
			"to": [10.375, 13, -0.75],
			"rotation": {"angle": 0, "axis": "y", "origin": [7.75, 2.5, -9]},
			"faces": {
				"north": {"uv": [6.6885, 1.0635, 7.28025, 1.124], "texture": "#1"},
				"east": {"uv": [7.15525, 5.3135, 6.8135, 5.374], "texture": "#1"},
				"south": {"uv": [6.8135, 0.4385, 7.40525, 0.499], "texture": "#1"},
				"west": {"uv": [6.8135, 5.3135, 7.15525, 5.374], "texture": "#1"},
				"up": {"uv": [6.90525, 6.53025, 6.3135, 6.1885], "texture": "#1"}
			}
		},
		{
			"from": [4.875, 12.2706, -4.84672],
			"to": [6.125, 13.2706, -3.84672],
			"rotation": {"angle": 22.5, "axis": "x", "origin": [8, 12.7706, -4.34672]},
			"faces": {
				"north": {"uv": [6.8135, 5.376, 6.96775, 5.499], "texture": "#1"},
				"east": {"uv": [6.876, 1.90725, 6.999, 2.03025], "texture": "#1"},
				"south": {"uv": [6.8135, 5.501, 6.96775, 5.624], "texture": "#1"},
				"west": {"uv": [6.876, 3.001, 6.999, 3.124], "texture": "#1"},
				"up": {"uv": [6.96775, 5.749, 6.8135, 5.626], "texture": "#1"}
			}
		},
		{
			"from": [9.875, 12.2706, -4.84672],
			"to": [11.125, 13.2706, -3.84672],
			"rotation": {"angle": 22.5, "axis": "x", "origin": [8, 12.7706, -4.34672]},
			"faces": {
				"north": {"uv": [6.96775, 5.376, 6.8135, 5.499], "texture": "#1"},
				"east": {"uv": [6.999, 3.001, 6.876, 3.124], "texture": "#1"},
				"south": {"uv": [6.96775, 5.501, 6.8135, 5.624], "texture": "#1"},
				"west": {"uv": [6.999, 1.90725, 6.876, 2.03025], "texture": "#1"},
				"up": {"uv": [6.8135, 5.749, 6.96775, 5.626], "texture": "#1"}
			}
		},
		{
			"from": [7.375, 12.2706, -4.84672],
			"to": [8.625, 13.2706, -3.84672],
			"rotation": {"angle": 22.5, "axis": "x", "origin": [8, 12.7706, -4.34672]},
			"faces": {
				"north": {"uv": [6.8135, 5.751, 6.96775, 5.874], "texture": "#1"},
				"east": {"uv": [6.876, 3.126, 6.999, 3.249], "texture": "#1"},
				"south": {"uv": [6.8135, 5.876, 6.96775, 5.999], "texture": "#1"},
				"west": {"uv": [6.876, 3.251, 6.999, 3.374], "texture": "#1"},
				"up": {"uv": [6.96775, 6.124, 6.8135, 6.001], "texture": "#1"}
			}
		},
		{
			"from": [0.25, 2.5, 21],
			"to": [3.25, 4, 21.5],
			"rotation": {"angle": 0, "axis": "y", "origin": [1.75, 2.5, 10.25]},
			"faces": {
				"east": {"uv": [0.1885, 6.9385, 0.249, 7.124], "texture": "#1"},
				"south": {"uv": [6.6885, 0.65725, 7.0615, 0.84275], "texture": "#1"},
				"west": {"uv": [0.251, 6.9385, 0.3115, 7.124], "texture": "#1"},
				"up": {"uv": [7.1865, 0.65525, 6.8135, 0.59475], "texture": "#1"},
				"down": {"uv": [7.1865, 5.251, 6.8135, 5.3115], "texture": "#1"}
			}
		},
		{
			"from": [7.75, 2.5, 18.25],
			"to": [8.25, 4.25, 20.5],
			"rotation": {"angle": 0, "axis": "y", "origin": [7.75, 2.5, 9.25]},
			"faces": {
				"north": {"uv": [4.876, 6.90725, 4.9365, 7.124], "texture": "#1"},
				"east": {"uv": [2.15725, 6.751, 2.4365, 6.96775], "texture": "#1"},
				"south": {"uv": [4.9385, 6.90725, 4.999, 7.124], "texture": "#1"},
				"west": {"uv": [2.4385, 6.751, 2.71775, 6.96775], "texture": "#1"},
				"up": {"uv": [6.78025, 7.124, 6.71975, 6.84475], "texture": "#1"},
				"down": {"uv": [6.84275, 6.84475, 6.78225, 7.124], "texture": "#1"}
			}
		},
		{
			"from": [2.25, 2.5, 18.25],
			"to": [2.75, 4.25, 20.5],
			"rotation": {"angle": 0, "axis": "y", "origin": [2.25, 2.5, 9.25]},
			"faces": {
				"north": {"uv": [5.001, 6.90725, 5.0615, 7.124], "texture": "#1"},
				"east": {"uv": [2.71975, 6.751, 2.999, 6.96775], "texture": "#1"},
				"south": {"uv": [6.90725, 6.126, 6.96775, 6.34275], "texture": "#1"},
				"west": {"uv": [3.001, 6.751, 3.28025, 6.96775], "texture": "#1"},
				"up": {"uv": [6.90525, 7.124, 6.84475, 6.84475], "texture": "#1"},
				"down": {"uv": [6.9365, 1.626, 6.876, 1.90525], "texture": "#1"}
			}
		},
		{
			"from": [13.25, 2.5, 18.25],
			"to": [13.75, 4.25, 20.5],
			"rotation": {"angle": 0, "axis": "y", "origin": [13.75, 2.5, 9.25]},
			"faces": {
				"north": {"uv": [5.0615, 6.90725, 5.001, 7.124], "texture": "#1"},
				"east": {"uv": [3.28025, 6.751, 3.001, 6.96775], "texture": "#1"},
				"south": {"uv": [6.96775, 6.126, 6.90725, 6.34275], "texture": "#1"},
				"west": {"uv": [2.999, 6.751, 2.71975, 6.96775], "texture": "#1"},
				"up": {"uv": [6.84475, 7.124, 6.90525, 6.84475], "texture": "#1"},
				"down": {"uv": [6.876, 1.626, 6.9365, 1.90525], "texture": "#1"}
			}
		},
		{
			"from": [12.75, 2.5, 21],
			"to": [15.75, 4, 21.5],
			"rotation": {"angle": 0, "axis": "y", "origin": [14.25, 2.5, 10.25]},
			"faces": {
				"east": {"uv": [0.3115, 6.9385, 0.251, 7.124], "texture": "#1"},
				"south": {"uv": [7.0615, 0.65725, 6.6885, 0.84275], "texture": "#1"},
				"west": {"uv": [0.249, 6.9385, 0.1885, 7.124], "texture": "#1"},
				"up": {"uv": [6.8135, 0.65525, 7.1865, 0.59475], "texture": "#1"},
				"down": {"uv": [6.8135, 5.251, 7.1865, 5.3115], "texture": "#1"}
			}
		},
		{
			"from": [1.43157, 1.1628, -3.25],
			"to": [4.43157, 2.1628, -0.25],
			"rotation": {"angle": -22.5, "axis": "z", "origin": [2.43157, 3.2878, 10]},
			"faces": {
				"north": {"uv": [4.6885, 6.78225, 5.0615, 6.90525], "texture": "#1"},
				"east": {"uv": [4.6885, 6.78225, 5.0615, 6.90525], "texture": "#1"},
				"south": {"uv": [4.6885, 6.78225, 5.0615, 6.90525], "texture": "#1"},
				"west": {"uv": [4.6885, 6.78225, 5.0615, 6.90525], "texture": "#1"}
			}
		},
		{
			"from": [-0.5494, 2.00847, 9],
			"to": [2.4506, 3.00847, 12],
			"rotation": {"angle": -22.5, "axis": "z", "origin": [0.2006, 4.13347, 22]},
			"faces": {
				"north": {"uv": [6.8135, 0.09475, 7.1865, 0.21775], "texture": "#1"},
				"east": {"uv": [6.8135, 0.09475, 7.1865, 0.21775], "texture": "#1"},
				"south": {"uv": [6.8135, 0.09475, 7.1865, 0.21775], "texture": "#1"},
				"west": {"uv": [6.8135, 0.09475, 7.1865, 0.21775], "texture": "#1"}
			}
		},
		{
			"from": [-1.08798, 2.31451, 13.5],
			"to": [2.91202, 3.31451, 17.5],
			"rotation": {"angle": -22.5, "axis": "z", "origin": [-0.58798, 4.43951, 26.25]},
			"faces": {
				"north": {"uv": [6.59475, 6.71975, 7.09275, 6.84275], "texture": "#1"},
				"east": {"uv": [6.59475, 6.71975, 7.09275, 6.84275], "texture": "#1"},
				"south": {"uv": [6.59475, 6.71975, 7.09275, 6.84275], "texture": "#1"},
				"west": {"uv": [6.59475, 6.71975, 7.09275, 6.84275], "texture": "#1"}
			}
		},
		{
			"from": [13.42336, 2.6353, 8.75],
			"to": [16.92336, 4.6353, 12.25],
			"rotation": {"angle": 22.5, "axis": "z", "origin": [14.92336, 3.6353, 10.75]},
			"faces": {
				"north": {"uv": [6.999, 4.626, 6.5635, 4.874], "texture": "#1"},
				"east": {"uv": [6.999, 4.626, 6.5635, 4.874], "texture": "#1"},
				"south": {"uv": [6.999, 4.626, 6.5635, 4.874], "texture": "#1"},
				"west": {"uv": [6.999, 4.626, 6.5635, 4.874], "texture": "#1"},
				"up": {"uv": [0.4385, 6.9365, 0.874, 6.501], "texture": "#1"},
				"down": {"uv": [0.876, 6.501, 1.3115, 6.9365], "texture": "#1"}
			}
		},
		{
			"from": [13.5494, 2.00847, 9],
			"to": [16.5494, 3.00847, 12],
			"rotation": {"angle": 22.5, "axis": "z", "origin": [15.7994, 4.13347, 22]},
			"faces": {
				"north": {"uv": [7.1865, 0.09475, 6.8135, 0.21775], "texture": "#1"},
				"east": {"uv": [7.1865, 0.09475, 6.8135, 0.21775], "texture": "#1"},
				"south": {"uv": [7.1865, 0.09475, 6.8135, 0.21775], "texture": "#1"},
				"west": {"uv": [7.1865, 0.09475, 6.8135, 0.21775], "texture": "#1"}
			}
		},
		{
			"from": [13, 2.75, 13.25],
			"to": [17.5, 4.75, 17.75],
			"rotation": {"angle": 22.5, "axis": "z", "origin": [15.25, 3.75, 15.5]},
			"faces": {
				"north": {"uv": [5.28025, 6.53225, 4.71975, 6.78025], "texture": "#1"},
				"east": {"uv": [5.28025, 6.53225, 4.71975, 6.78025], "texture": "#1"},
				"south": {"uv": [5.28025, 6.53225, 4.71975, 6.78025], "texture": "#1"},
				"west": {"uv": [5.28025, 6.53225, 4.71975, 6.78025], "texture": "#1"},
				"up": {"uv": [6.126, 0.5615, 6.6865, 0.001], "texture": "#1"},
				"down": {"uv": [6.126, 0.5635, 6.6865, 1.124], "texture": "#1"}
			}
		},
		{
			"from": [13.08798, 2.31451, 13.5],
			"to": [17.08798, 3.31451, 17.5],
			"rotation": {"angle": 22.5, "axis": "z", "origin": [16.58798, 4.43951, 26.25]},
			"faces": {
				"north": {"uv": [7.09275, 6.71975, 6.59475, 6.84275], "texture": "#1"},
				"east": {"uv": [7.09275, 6.71975, 6.59475, 6.84275], "texture": "#1"},
				"south": {"uv": [7.09275, 6.71975, 6.59475, 6.84275], "texture": "#1"},
				"west": {"uv": [7.09275, 6.71975, 6.59475, 6.84275], "texture": "#1"}
			}
		},
		{
			"from": [11.40433, 1.98097, -3.5],
			"to": [14.90433, 3.98097, 0],
			"rotation": {"angle": 22.5, "axis": "z", "origin": [13.15433, 2.98097, -1.75]},
			"faces": {
				"north": {"uv": [6.999, 4.376, 6.5635, 4.624], "texture": "#1"},
				"east": {"uv": [6.999, 4.376, 6.5635, 4.624], "texture": "#1"},
				"south": {"uv": [6.999, 4.376, 6.5635, 4.624], "texture": "#1"},
				"west": {"uv": [6.999, 4.376, 6.5635, 4.624], "texture": "#1"},
				"up": {"uv": [6.4385, 2.0615, 6.874, 1.626], "texture": "#1"},
				"down": {"uv": [0.001, 6.501, 0.4365, 6.9365], "texture": "#1"}
			}
		},
		{
			"from": [11.56843, 1.1628, -3.25],
			"to": [14.56843, 2.1628, -0.25],
			"rotation": {"angle": 22.5, "axis": "z", "origin": [13.56843, 3.2878, 10]},
			"faces": {
				"north": {"uv": [5.0615, 6.78225, 4.6885, 6.90525], "texture": "#1"},
				"east": {"uv": [5.0615, 6.78225, 4.6885, 6.90525], "texture": "#1"},
				"south": {"uv": [5.0615, 6.78225, 4.6885, 6.90525], "texture": "#1"},
				"west": {"uv": [5.0615, 6.78225, 4.6885, 6.90525], "texture": "#1"}
			}
		}
	],
	"display": {
		"thirdperson_righthand": {
			"rotation": [75, 45, 0],
			"translation": [0, 2.5, 0],
			"scale": [0.375, 0.375, 0.375]
		},
		"thirdperson_lefthand": {
			"rotation": [75, 45, 0],
			"translation": [0, 2.5, 0],
			"scale": [0.375, 0.375, 0.375]
		},
		"firstperson_righthand": {
			"rotation": [0, 45, 0],
			"scale": [0.4, 0.4, 0.4]
		},
		"firstperson_lefthand": {
			"rotation": [0, 225, 0],
			"scale": [0.4, 0.4, 0.4]
		},
		"ground": {
			"translation": [0, 3, 0],
			"scale": [0.25, 0.25, 0.25]
		},
		"gui": {
			"rotation": [30, 225, 0],
			"translation": [0, -0.5, 0],
			"scale": [0.48, 0.48, 0.48]
		},
		"fixed": {
			"scale": [0.5, 0.5, 0.5]
		}
	},
	"groups": [
		{
			"name": "Truck",
			"origin": [8.25, 6, -51],
			"color": 0,
			"boneType": "",
			"children": [
				0,
				1,
				2,
				3,
				4,
				5,
				6,
				7,
				8,
				9,
				10,
				11,
				12,
				13,
				14,
				15,
				16,
				17,
				18,
				19,
				20,
				21,
				22,
				23,
				24,
				25,
				26,
				27,
				28,
				29,
				30,
				31,
				32,
				33,
				34,
				35,
				36,
				37,
				38,
				39,
				40,
				41,
				42,
				43,
				44,
				45,
				46,
				47,
				48,
				49,
				50,
				51,
				52,
				53,
				54,
				55,
				56,
				57
			]
		}
	]
}