{
	"credit": "Made by Ziqqy using Blockbench",
	"parent": "walmart:display_parents/furniture",
	"texture_size": [256, 256],
	"textures": {
		"0": "walmart:furniture/ship_crate",
		"particle": "walmart:furniture/ship_crate"
	},
	"elements": [
		{
			"from": [3.75, 3.25, 3.75],
			"to": [6.25, 4, 12.25],
			"rotation": {"angle": 0, "axis": "y", "origin": [6, 0, 6]},
			"faces": {
				"north": {"uv": [2.6895, 2.127, 3.3105, 2.3105], "texture": "#0"},
				"east": {"uv": [1.0645, 2.8145, 3.1855, 2.998], "texture": "#0"},
				"south": {"uv": [3.3105, 2.127, 2.6895, 2.3105], "texture": "#0"},
				"west": {"uv": [1.0645, 1.6895, 3.1855, 1.873], "texture": "#0"},
				"up": {"uv": [4.373, 2.123, 3.752, 0.002], "texture": "#0"},
				"down": {"uv": [5.623, 0.002, 5.002, 2.123], "texture": "#0"}
			}
		},
		{
			"from": [6.25, 3.25, 4.75],
			"to": [9.75, 4, 11.25],
			"rotation": {"angle": 0, "axis": "y", "origin": [6, -0.75, 6]},
			"faces": {
				"north": {"uv": [2.6895, 1.9395, 3.5605, 2.123], "texture": "#0"},
				"south": {"uv": [2.6895, 1.9395, 3.5605, 2.123], "texture": "#0"},
				"up": {"uv": [2.873, 1.623, 2.002, 0.002], "texture": "#0"},
				"down": {"uv": [3.748, 0.002, 2.877, 1.623], "texture": "#0"}
			}
		},
		{
			"from": [9.75, 3.25, 3.75],
			"to": [12.25, 4, 12.25],
			"rotation": {"angle": 0, "axis": "y", "origin": [10, 0, 6]},
			"faces": {
				"north": {"uv": [3.3105, 2.127, 2.6895, 2.3105], "texture": "#0"},
				"east": {"uv": [3.1855, 1.6895, 1.0645, 1.873], "texture": "#0"},
				"south": {"uv": [2.6895, 2.127, 3.3105, 2.3105], "texture": "#0"},
				"west": {"uv": [3.1855, 2.8145, 1.0645, 2.998], "texture": "#0"},
				"up": {"uv": [3.752, 2.123, 4.373, 0.002], "texture": "#0"},
				"down": {"uv": [5.002, 0.002, 5.623, 2.123], "texture": "#0"}
			}
		},
		{
			"from": [4, 0, 4],
			"to": [6, 3.25, 12],
			"rotation": {"angle": 0, "axis": "y", "origin": [6, 0, 6]},
			"faces": {
				"north": {"uv": [1.0645, 1.9395, 1.5605, 2.748], "texture": "#0"},
				"east": {"uv": [0.002, 0.002, 1.998, 0.8105], "texture": "#0"},
				"south": {"uv": [1.5605, 1.9395, 1.0645, 2.748], "texture": "#0"},
				"west": {"uv": [0.002, 0.8145, 1.998, 1.623], "texture": "#0"},
				"down": {"uv": [7.9355, 1.627, 7.4395, 3.623], "texture": "#0"}
			}
		},
		{
			"from": [6, 0, 5],
			"to": [10, 3.25, 11],
			"rotation": {"angle": 0, "axis": "y", "origin": [6, 0, 6]},
			"faces": {
				"north": {"uv": [1.627, 1.9395, 2.623, 2.748], "texture": "#0"},
				"south": {"uv": [1.627, 1.9395, 2.623, 2.748], "texture": "#0"},
				"down": {"uv": [7.998, 0.002, 7.002, 1.498], "texture": "#0"}
			}
		},
		{
			"from": [10, 0, 4],
			"to": [12, 3.25, 12],
			"rotation": {"angle": 0, "axis": "y", "origin": [10, 0, 6]},
			"faces": {
				"north": {"uv": [1.5605, 1.9395, 1.0645, 2.748], "texture": "#0"},
				"east": {"uv": [1.998, 0.8145, 0.002, 1.623], "texture": "#0"},
				"south": {"uv": [1.0645, 1.9395, 1.5605, 2.748], "texture": "#0"},
				"west": {"uv": [1.998, 0.002, 0.002, 0.8105], "texture": "#0"},
				"down": {"uv": [7.4395, 1.627, 7.9355, 3.623], "texture": "#0"}
			}
		},
		{
			"name": "cube inverted",
			"from": [10, 4, 11],
			"to": [6, 0.5, 5],
			"rotation": {"angle": 0, "axis": "y", "origin": [6, 0.5, 6]},
			"faces": {
				"north": {"uv": [5.4395, 3.123, 6.4355, 2.252], "texture": "#0"},
				"south": {"uv": [5.4395, 3.123, 6.4355, 2.252], "texture": "#0"},
				"up": {"uv": [5.6895, 1.498, 6.6855, 0.002], "texture": "#0"}
			}
		},
		{
			"name": "cube inverted",
			"from": [12, 4, 12],
			"to": [10, 0.5, 4],
			"rotation": {"angle": 0, "axis": "y", "origin": [10, 0.5, 6]},
			"faces": {
				"north": {"uv": [6.502, 3.123, 6.998, 2.252], "texture": "#0"},
				"east": {"uv": [3.0605, 3.998, 1.0645, 3.127], "texture": "#0"},
				"south": {"uv": [6.998, 3.123, 6.502, 2.252], "texture": "#0"},
				"west": {"uv": [5.373, 3.123, 3.377, 2.252], "texture": "#0"},
				"up": {"uv": [4.9355, 1.998, 4.4395, 0.002], "texture": "#0"}
			}
		},
		{
			"name": "cube inverted",
			"from": [6, 4, 12],
			"to": [4, 0.5, 4],
			"rotation": {"angle": 0, "axis": "y", "origin": [6, 0.5, 6]},
			"faces": {
				"north": {"uv": [6.998, 3.123, 6.502, 2.252], "texture": "#0"},
				"east": {"uv": [3.377, 3.123, 5.373, 2.252], "texture": "#0"},
				"south": {"uv": [6.502, 3.123, 6.998, 2.252], "texture": "#0"},
				"west": {"uv": [1.0645, 3.998, 3.0605, 3.127], "texture": "#0"},
				"up": {"uv": [4.4395, 1.998, 4.9355, 0.002], "texture": "#0"}
			}
		}
	],
	"display": {
		"gui": {
			"rotation": [30, 225, 0],
			"translation": [0, 6.75, 0],
			"scale": [1.19, 1.19, 1.19]
		}
	},
	"groups": [
		{
			"name": "rim",
			"origin": [16, 0, 0],
			"color": 0,
			"boneType": "",
			"children": [0, 1, 2]
		},
		{
			"name": "outside",
			"origin": [16, 0, 0],
			"color": 0,
			"boneType": "",
			"children": [3, 4, 5]
		},
		{
			"name": "inside",
			"origin": [0, 0, 0],
			"color": 0,
			"boneType": "",
			"children": [6, 7, 8]
		}
	]
}